LICENSE
MANIFEST.in
README.md
banner.jpg
setup.py
lv_linkpy.egg-info/PKG-INFO
lv_linkpy.egg-info/SOURCES.txt
lv_linkpy.egg-info/dependency_links.txt
lv_linkpy.egg-info/requires.txt
lv_linkpy.egg-info/top_level.txt
lvlinkpy/__init__.py
lvlinkpy/lvlinkpy.py