Metadata-Version: 2.1
Name: lv-linkpy
Version: 1.0.2
Summary: a python interface to remote LabVIEW controls
Author: ZHUO DIAO
Author-email: enzian0515@gmail.com
License: MIT
Requires-Python: >=3.6
License-File: LICENSE
